LICENSE.md
MANIFEST.in
readme.md
setup.py
simple_NER/__init__.py
simple_NER/settings.py
simple_NER.egg-info/PKG-INFO
simple_NER.egg-info/SOURCES.txt
simple_NER.egg-info/dependency_links.txt
simple_NER.egg-info/requires.txt
simple_NER.egg-info/top_level.txt
simple_NER/__pycache__/__init__.cpython-38.pyc
simple_NER/__pycache__/settings.cpython-38.pyc
simple_NER/annotators/__init__.py
simple_NER/annotators/datetime_ner.py
simple_NER/annotators/email_ner.py
simple_NER/annotators/keyword_ner.py
simple_NER/annotators/locations_ner.py
simple_NER/annotators/lookup_ner.py
simple_NER/annotators/names_ner.py
simple_NER/annotators/nltk_ner.py
simple_NER/annotators/numbers_ner.py
simple_NER/annotators/snips_ner.py
simple_NER/annotators/units_ner.py
simple_NER/annotators/__pycache__/__init__.cpython-38.pyc
simple_NER/annotators/__pycache__/units_ner.cpython-38.pyc
simple_NER/annotators/remote/__init__.py
simple_NER/annotators/remote/dbpedia.py
simple_NER/annotators/remote/polyglot_demo.py
simple_NER/annotators/remote/spacy_demo.py
simple_NER/keywords/__init__.py
simple_NER/keywords/rake.py
simple_NER/keywords/__pycache__/__init__.cpython-38.pyc
simple_NER/keywords/__pycache__/rake.cpython-38.pyc
simple_NER/res/cities.json
simple_NER/res/countries.json
simple_NER/res/en-us/FoxStoplist.txt
simple_NER/res/en-us/SmartStoplist.txt
simple_NER/res/en-us/age_property.entity
simple_NER/res/en-us/animal.entity
simple_NER/res/en-us/appearance_property.entity
simple_NER/res/en-us/character_property.entity
simple_NER/res/en-us/cities.entity
simple_NER/res/en-us/color.entity
simple_NER/res/en-us/countries.entity
simple_NER/res/en-us/dog.entity
simple_NER/res/en-us/emotion.entity
simple_NER/res/en-us/month.entity
simple_NER/res/en-us/weather.entity
simple_NER/rules/__init__.py
simple_NER/rules/neural.py
simple_NER/rules/rx.py
simple_NER/rules/__pycache__/__init__.cpython-38.pyc
simple_NER/rules/__pycache__/rx.cpython-38.pyc
simple_NER/utils/__init__.py
simple_NER/utils/diff.py
simple_NER/utils/log.py
simple_NER/utils/__pycache__/__init__.cpython-38.pyc
simple_NER/utils/__pycache__/diff.cpython-38.pyc
simple_NER/utils/__pycache__/log.cpython-38.pyc