Metadata-Version: 2.1
Name: simple-NER
Version: 0.8.0
Summary: rule based NER
Home-page: https://github.com/OpenJarbas/simple_NER
Author: jarbasAI
Author-email: jarbasai@mailfence.com
License: MIT
Platform: UNKNOWN
License-File: LICENSE.md
